Jalo
MANIFEST.in
README
setup.py
Jalapeno/Globalvar.py
Jalapeno/__init__.py
Jalapeno/core.py
Jalapeno/path.py
Jalapeno.egg-info/PKG-INFO
Jalapeno.egg-info/SOURCES.txt
Jalapeno.egg-info/dependency_links.txt
Jalapeno.egg-info/requires.txt
Jalapeno.egg-info/top_level.txt
Jalapeno/../Jalapeno_data/.DS_Store
Jalapeno/../Jalapeno_data/JaloLite.spec
Jalapeno/../Jalapeno_data/Sites/.DS_Store
Jalapeno/../Jalapeno_data/Sites/.siterc
Jalapeno/../Jalapeno_data/Sites/first/.DS_Store
Jalapeno/../Jalapeno_data/Sites/first/Pages/.DS_Store
Jalapeno/../Jalapeno_data/Sites/first/Pages/test 2.md
Jalapeno/../Jalapeno_data/Sites/first/Pages/test2.md
Jalapeno/../Jalapeno_data/Sites/first/Pages/blog/1.md
Jalapeno/../Jalapeno_data/Sites/first/Pages/blog/10.md
Jalapeno/../Jalapeno_data/Sites/first/Pages/blog/11.md
Jalapeno/../Jalapeno_data/Sites/first/Pages/blog/12.md
Jalapeno/../Jalapeno_data/Sites/first/Pages/blog/13.md
Jalapeno/../Jalapeno_data/Sites/first/Pages/blog/14.md
Jalapeno/../Jalapeno_data/Sites/first/Pages/blog/15.md
Jalapeno/../Jalapeno_data/Sites/first/Pages/blog/16.md
Jalapeno/../Jalapeno_data/Sites/first/Pages/blog/17.md
Jalapeno/../Jalapeno_data/Sites/first/Pages/blog/18.md
Jalapeno/../Jalapeno_data/Sites/first/Pages/blog/19.md
Jalapeno/../Jalapeno_data/Sites/first/Pages/blog/2.md
Jalapeno/../Jalapeno_data/Sites/first/Pages/blog/20.md
Jalapeno/../Jalapeno_data/Sites/first/Pages/blog/3.md
Jalapeno/../Jalapeno_data/Sites/first/Pages/blog/4.md
Jalapeno/../Jalapeno_data/Sites/first/Pages/blog/5.md
Jalapeno/../Jalapeno_data/Sites/first/Pages/blog/6.md
Jalapeno/../Jalapeno_data/Sites/first/Pages/blog/7.md
Jalapeno/../Jalapeno_data/Sites/first/Pages/blog/8.md
Jalapeno/../Jalapeno_data/Sites/first/Pages/blog/9.md
Jalapeno/../Jalapeno_data/Sites/first/Pages/blog/getstart.md
Jalapeno/../Jalapeno_data/Sites/first/Pages/doc/config.md
Jalapeno/../Jalapeno_data/Sites/first/Pages/doc/install.md
Jalapeno/../Jalapeno_data/Sites/first/Pages/doc/shortcutdir.md
Jalapeno/../Jalapeno_data/Sites/first/Pages/doc/test.md
Jalapeno/../Jalapeno_data/Sites/first/Pages/doc/writing.md
Jalapeno/../Jalapeno_data/Sites/first/Pages/markpages/.DS_Store
