Metadata-Version: 1.0
Name: Jalapeno
Version: 0.1.4
Summary: Static Site Generator based on Flask
Home-page: https://github.com/ChenghaoQ/Jalapeno
Author: Chenghao Qian
Author-email: qch.jacob.jm@gmail.com
License: LGPL
Keywords: Flask,Blog,site Generator,static site
Platform: UNKNOWN
